README.rst
setup.py
categorytree/admin.py
categorytree/apps.py
categorytree/forms.py
categorytree/models.py
categorytree/tests.py
django_categorytree.egg-info/PKG-INFO
django_categorytree.egg-info/SOURCES.txt
django_categorytree.egg-info/dependency_links.txt
django_categorytree.egg-info/top_level.txt