Metadata-Version: 1.1
Name: django-categorytree
Version: 0.1.1
Summary: A django app with an abstract model which helps to define tree style categories with unlimited sub levels
Home-page: https://github.com/payamnj/django-categorytree
Author: Payam Najafizadeh
Author-email: payam.nj@gmail.com
License: New BSD
Platform: UNKNOWN
Classifier: Programming Language :: Python
Classifier: Operating System :: OS Independent
Classifier: Environment :: Web Environment
Classifier: Framework :: Django
Requires: django(>=1.8)
